{
  "module": "apps/docs/components/geistdocs/installer.tsx",
  "symbols": [
    {
      "children": [],
      "id": "apps/docs/components/geistdocs/installer.tsx:COPY_TIMEOUT",
      "kind": "variable",
      "line_range": [
        14,
        14
      ],
      "name": "COPY_TIMEOUT",
      "partial_analysis": false,
      "value": "",
      "visibility": "Private"
    },
    {
      "children": [
        {
          "children": [],
          "id": "apps/docs/components/geistdocs/installer.tsx:InstallerProps:className",
          "kind": "property",
          "line_range": [
            17,
            17
          ],
          "name": "className",
          "partial_analysis": false,
          "return_type": ": string",
          "visibility": "Public"
        },
        {
          "children": [],
          "id": "apps/docs/components/geistdocs/installer.tsx:InstallerProps:command",
          "kind": "property",
          "line_range": [
            18,
            18
          ],
          "name": "command",
          "partial_analysis": false,
          "return_type": ": string",
          "visibility": "Public"
        }
      ],
      "id": "apps/docs/components/geistdocs/installer.tsx:InstallerProps",
      "kind": "interface",
      "line_range": [
        16,
        19
      ],
      "name": "InstallerProps",
      "partial_analysis": false,
      "visibility": "Private"
    },
    {
      "children": [],
      "id": "apps/docs/components/geistdocs/installer.tsx:Installer",
      "is_async": false,
      "kind": "variable",
      "line_range": [
        21,
        57
      ],
      "name": "Installer",
      "params": [
        {
          "name": "_",
          "optional": false,
          "type": "InstallerProps"
        }
      ],
      "partial_analysis": false,
      "value": "",
      "visibility": "Public"
    }
  ]
}