{
  "module": "apps/templates/web-chat-next/components/ai-elements/code-block.tsx",
  "symbols": [
    {
      "children": [],
      "id": "apps/templates/web-chat-next/components/ai-elements/code-block.tsx:isItalic",
      "is_async": false,
      "kind": "variable",
      "line_range": [
        29,
        29
      ],
      "name": "isItalic",
      "params": [
        {
          "name": "fontStyle",
          "optional": false,
          "type": "number | undefined"
        }
      ],
      "partial_analysis": false,
      "value": "",
      "visibility": "Private"
    },
    {
      "children": [],
      "id": "apps/templates/web-chat-next/components/ai-elements/code-block.tsx:isBold",
      "is_async": false,
      "kind": "variable",
      "line_range": [
        31,
        31
      ],
      "name": "isBold",
      "params": [
        {
          "name": "fontStyle",
          "optional": false,
          "type": "number | undefined"
        }
      ],
      "partial_analysis": false,
      "value": "",
      "visibility": "Private"
    },
    {
      "children": [],
      "id": "apps/templates/web-chat-next/components/ai-elements/code-block.tsx:isUnderline",
      "is_async": false,
      "kind": "variable",
      "line_range": [
        32,
        34
      ],
      "name": "isUnderline",
      "params": [
        {
          "name": "fontStyle",
          "optional": false,
          "type": "number | undefined"
        }
      ],
      "partial_analysis": false,
      "value": "",
      "visibility": "Private"
    },
    {
      "children": [
        {
          "children": [],
          "id": "apps/templates/web-chat-next/components/ai-elements/code-block.tsx:KeyedToken:token",
          "kind": "property",
          "line_range": [
            38,
            38
          ],
          "name": "token",
          "partial_analysis": false,
          "return_type": ": ThemedToken",
          "visibility": "Public"
        },
        {
          "children": [],
          "id": "apps/templates/web-chat-next/components/ai-elements/code-block.tsx:KeyedToken:key",
          "kind": "property",
          "line_range": [
            39,
            39
          ],
          "name": "key",
          "partial_analysis": false,
          "return_type": ": string",
          "visibility": "Public"
        }
      ],
      "id": "apps/templates/web-chat-next/components/ai-elements/code-block.tsx:KeyedToken",
      "kind": "interface",
      "line_range": [
        37,
        40
      ],
      "name": "KeyedToken",
      "partial_analysis": false,
      "visibility": "Private"
    },
    {
      "children": [
        {
          "children": [],
          "id": "apps/templates/web-chat-next/components/ai-elements/code-block.tsx:KeyedLine:tokens",
          "kind": "property",
          "line_range": [
            42,
            42
          ],
          "name": "tokens",
          "partial_analysis": false,
          "return_type": ": KeyedToken[]",
          "visibility": "Public"
        },
        {
          "children": [],
          "id": "apps/templates/web-chat-next/components/ai-elements/code-block.tsx:KeyedLine:key",
          "kind": "property",
          "line_range": [
            43,
            43
          ],
          "name": "key",
          "partial_analysis": false,
          "return_type": ": string",
          "visibility": "Public"
        }
      ],
      "id": "apps/templates/web-chat-next/components/ai-elements/code-block.tsx:KeyedLine",
      "kind": "interface",
      "line_range": [
        41,
        44
      ],
      "name": "KeyedLine",
      "partial_analysis": false,
      "visibility": "Private"
    },
    {
      "children": [],
      "id": "apps/templates/web-chat-next/components/ai-elements/code-block.tsx:addKeysToTokens",
      "is_async": false,
      "kind": "variable",
      "line_range": [
        46,
        53
      ],
      "name": "addKeysToTokens",
      "params": [
        {
          "name": "lines",
          "optional": false,
          "type": "ThemedToken[][]"
        }
      ],
      "partial_analysis": false,
      "return_type": "KeyedLine[]",
      "value": "",
      "visibility": "Private"
    },
    {
      "children": [],
      "id": "apps/templates/web-chat-next/components/ai-elements/code-block.tsx:TokenSpan",
      "is_async": false,
      "kind": "variable",
      "line_range": [
        56,
        72
      ],
      "name": "TokenSpan",
      "params": [
        {
          "name": "_",
          "optional": false,
          "type": "{ token: ThemedToken }"
        }
      ],
      "partial_analysis": false,
      "value": "",
      "visibility": "Private"
    },
    {
      "children": [],
      "id": "apps/templates/web-chat-next/components/ai-elements/code-block.tsx:LINE_NUMBER_CLASSES",
      "kind": "variable",
      "line_range": [
        75,
        86
      ],
      "name": "LINE_NUMBER_CLASSES",
      "partial_analysis": false,
      "value": "",
      "visibility": "Private"
    },
    {
      "children": [],
      "id": "apps/templates/web-chat-next/components/ai-elements/code-block.tsx:LineSpan",
      "is_async": false,
      "kind": "variable",
      "line_range": [
        89,
        101
      ],
      "name": "LineSpan",
      "params": [
        {
          "name": "_",
          "optional": false,
          "type": "{\r\n  keyedLine: KeyedLine;\r\n  showLineNumbers: boolean;\r\n}"
        }
      ],
      "partial_analysis": false,
      "value": "",
      "visibility": "Private"
    },
    {
      "children": [],
      "id": "apps/templates/web-chat-next/components/ai-elements/code-block.tsx:CodeBlockProps",
      "kind": "type_alias",
      "line_range": [
        104,
        108
      ],
      "name": "CodeBlockProps",
      "partial_analysis": false,
      "value": "HTMLAttributes<HTMLDivElement> & {\r\n  code: string;\r\n  language: BundledLanguage;\r\n  showLineNumbers?: boolean;\r\n};",
      "visibility": "Private"
    },
    {
      "children": [
        {
          "children": [],
          "id": "apps/templates/web-chat-next/components/ai-elements/code-block.tsx:TokenizedCode:tokens",
          "kind": "property",
          "line_range": [
            111,
            111
          ],
          "name": "tokens",
          "partial_analysis": false,
          "return_type": ": ThemedToken[][]",
          "visibility": "Public"
        },
        {
          "children": [],
          "id": "apps/templates/web-chat-next/components/ai-elements/code-block.tsx:TokenizedCode:fg",
          "kind": "property",
          "line_range": [
            112,
            112
          ],
          "name": "fg",
          "partial_analysis": false,
          "return_type": ": string",
          "visibility": "Public"
        },
        {
          "children": [],
          "id": "apps/templates/web-chat-next/components/ai-elements/code-block.tsx:TokenizedCode:bg",
          "kind": "property",
          "line_range": [
            113,
            113
          ],
          "name": "bg",
          "partial_analysis": false,
          "return_type": ": string",
          "visibility": "Public"
        }
      ],
      "id": "apps/templates/web-chat-next/components/ai-elements/code-block.tsx:TokenizedCode",
      "kind": "interface",
      "line_range": [
        110,
        114
      ],
      "name": "TokenizedCode",
      "partial_analysis": false,
      "visibility": "Private"
    },
    {
      "children": [
        {
          "children": [],
          "id": "apps/templates/web-chat-next/components/ai-elements/code-block.tsx:CodeBlockContextType:code",
          "kind": "property",
          "line_range": [
            117,
            117
          ],
          "name": "code",
          "partial_analysis": false,
          "return_type": ": string",
          "visibility": "Public"
        }
      ],
      "id": "apps/templates/web-chat-next/components/ai-elements/code-block.tsx:CodeBlockContextType",
      "kind": "interface",
      "line_range": [
        116,
        118
      ],
      "name": "CodeBlockContextType",
      "partial_analysis": false,
      "visibility": "Private"
    },
    {
      "children": [],
      "id": "apps/templates/web-chat-next/components/ai-elements/code-block.tsx:CodeBlockContext",
      "kind": "variable",
      "line_range": [
        121,
        123
      ],
      "name": "CodeBlockContext",
      "partial_analysis": false,
      "value": "",
      "visibility": "Private"
    },
    {
      "children": [],
      "id": "apps/templates/web-chat-next/components/ai-elements/code-block.tsx:highlighterCache",
      "kind": "variable",
      "line_range": [
        126,
        129
      ],
      "name": "highlighterCache",
      "partial_analysis": false,
      "value": "",
      "visibility": "Private"
    },
    {
      "children": [],
      "id": "apps/templates/web-chat-next/components/ai-elements/code-block.tsx:tokensCache",
      "kind": "variable",
      "line_range": [
        132,
        132
      ],
      "name": "tokensCache",
      "partial_analysis": false,
      "value": "",
      "visibility": "Private"
    },
    {
      "children": [],
      "id": "apps/templates/web-chat-next/components/ai-elements/code-block.tsx:subscribers",
      "kind": "variable",
      "line_range": [
        135,
        135
      ],
      "name": "subscribers",
      "partial_analysis": false,
      "value": "",
      "visibility": "Private"
    },
    {
      "children": [],
      "id": "apps/templates/web-chat-next/components/ai-elements/code-block.tsx:getTokensCacheKey",
      "is_async": false,
      "kind": "variable",
      "line_range": [
        137,
        141
      ],
      "name": "getTokensCacheKey",
      "params": [
        {
          "name": "code",
          "optional": false,
          "type": "string"
        },
        {
          "name": "language",
          "optional": false,
          "type": "BundledLanguage"
        }
      ],
      "partial_analysis": false,
      "value": "",
      "visibility": "Private"
    },
    {
      "children": [],
      "id": "apps/templates/web-chat-next/components/ai-elements/code-block.tsx:getHighlighter",
      "is_async": false,
      "kind": "variable",
      "line_range": [
        143,
        158
      ],
      "name": "getHighlighter",
      "params": [
        {
          "name": "language",
          "optional": false,
          "type": "BundledLanguage"
        }
      ],
      "partial_analysis": false,
      "return_type": "Promise<HighlighterGeneric<BundledLanguage, BundledTheme>>",
      "value": "",
      "visibility": "Private"
    },
    {
      "children": [],
      "id": "apps/templates/web-chat-next/components/ai-elements/code-block.tsx:createRawTokens",
      "is_async": false,
      "kind": "variable",
      "line_range": [
        161,
        174
      ],
      "name": "createRawTokens",
      "params": [
        {
          "name": "code",
          "optional": false,
          "type": "string"
        }
      ],
      "partial_analysis": false,
      "return_type": "TokenizedCode",
      "value": "",
      "visibility": "Private"
    },
    {
      "children": [],
      "id": "apps/templates/web-chat-next/components/ai-elements/code-block.tsx:highlightCode",
      "is_async": false,
      "kind": "variable",
      "line_range": [
        177,
        239
      ],
      "name": "highlightCode",
      "params": [
        {
          "name": "code",
          "optional": false,
          "type": "string"
        },
        {
          "name": "language",
          "optional": false,
          "type": "BundledLanguage"
        },
        {
          "name": "callback",
          "optional": true,
          "type": "(result: TokenizedCode) => void"
        }
      ],
      "partial_analysis": false,
      "return_type": "TokenizedCode | null",
      "value": "",
      "visibility": "Public"
    },
    {
      "children": [],
      "id": "apps/templates/web-chat-next/components/ai-elements/code-block.tsx:CodeBlockBody",
      "kind": "variable",
      "line_range": [
        241,
        286
      ],
      "name": "CodeBlockBody",
      "partial_analysis": false,
      "value": "",
      "visibility": "Private"
    },
    {
      "children": [],
      "id": "apps/templates/web-chat-next/components/ai-elements/code-block.tsx:CodeBlockContainer",
      "is_async": false,
      "kind": "variable",
      "line_range": [
        290,
        309
      ],
      "name": "CodeBlockContainer",
      "params": [
        {
          "name": "_",
          "optional": false,
          "type": "HTMLAttributes<HTMLDivElement> & { language: string }"
        }
      ],
      "partial_analysis": false,
      "value": "",
      "visibility": "Public"
    },
    {
      "children": [],
      "id": "apps/templates/web-chat-next/components/ai-elements/code-block.tsx:CodeBlockHeader",
      "is_async": false,
      "kind": "variable",
      "line_range": [
        311,
        325
      ],
      "name": "CodeBlockHeader",
      "params": [
        {
          "name": "_",
          "optional": false,
          "type": "HTMLAttributes<HTMLDivElement>"
        }
      ],
      "partial_analysis": false,
      "value": "",
      "visibility": "Public"
    },
    {
      "children": [],
      "id": "apps/templates/web-chat-next/components/ai-elements/code-block.tsx:CodeBlockTitle",
      "is_async": false,
      "kind": "variable",
      "line_range": [
        327,
        335
      ],
      "name": "CodeBlockTitle",
      "params": [
        {
          "name": "_",
          "optional": false,
          "type": "HTMLAttributes<HTMLDivElement>"
        }
      ],
      "partial_analysis": false,
      "value": "",
      "visibility": "Public"
    },
    {
      "children": [],
      "id": "apps/templates/web-chat-next/components/ai-elements/code-block.tsx:CodeBlockFilename",
      "is_async": false,
      "kind": "variable",
      "line_range": [
        337,
        345
      ],
      "name": "CodeBlockFilename",
      "params": [
        {
          "name": "_",
          "optional": false,
          "type": "HTMLAttributes<HTMLSpanElement>"
        }
      ],
      "partial_analysis": false,
      "value": "",
      "visibility": "Public"
    },
    {
      "children": [],
      "id": "apps/templates/web-chat-next/components/ai-elements/code-block.tsx:CodeBlockActions",
      "is_async": false,
      "kind": "variable",
      "line_range": [
        347,
        355
      ],
      "name": "CodeBlockActions",
      "params": [
        {
          "name": "_",
          "optional": false,
          "type": "HTMLAttributes<HTMLDivElement>"
        }
      ],
      "partial_analysis": false,
      "value": "",
      "visibility": "Public"
    },
    {
      "children": [],
      "id": "apps/templates/web-chat-next/components/ai-elements/code-block.tsx:CodeBlockContent",
      "is_async": false,
      "kind": "variable",
      "line_range": [
        357,
        406
      ],
      "name": "CodeBlockContent",
      "params": [
        {
          "name": "_",
          "optional": false,
          "type": "{\r\n  code: string;\r\n  language: BundledLanguage;\r\n  showLineNumbers?: boolean;\r\n}"
        }
      ],
      "partial_analysis": false,
      "value": "",
      "visibility": "Public"
    },
    {
      "children": [],
      "id": "apps/templates/web-chat-next/components/ai-elements/code-block.tsx:CodeBlock",
      "is_async": false,
      "kind": "variable",
      "line_range": [
        408,
        426
      ],
      "name": "CodeBlock",
      "params": [
        {
          "name": "_",
          "optional": false,
          "type": "CodeBlockProps"
        }
      ],
      "partial_analysis": false,
      "value": "",
      "visibility": "Public"
    },
    {
      "children": [],
      "id": "apps/templates/web-chat-next/components/ai-elements/code-block.tsx:CodeBlockCopyButtonProps",
      "kind": "type_alias",
      "line_range": [
        428,
        432
      ],
      "name": "CodeBlockCopyButtonProps",
      "partial_analysis": false,
      "value": "ComponentProps<typeof Button> & {\r\n  onCopy?: () => void;\r\n  onError?: (error: Error) => void;\r\n  timeout?: number;\r\n};",
      "visibility": "Public"
    },
    {
      "children": [],
      "id": "apps/templates/web-chat-next/components/ai-elements/code-block.tsx:CodeBlockCopyButton",
      "is_async": false,
      "kind": "variable",
      "line_range": [
        434,
        484
      ],
      "name": "CodeBlockCopyButton",
      "params": [
        {
          "name": "_",
          "optional": false,
          "type": "CodeBlockCopyButtonProps"
        }
      ],
      "partial_analysis": false,
      "value": "",
      "visibility": "Public"
    },
    {
      "children": [],
      "id": "apps/templates/web-chat-next/components/ai-elements/code-block.tsx:CodeBlockLanguageSelectorProps",
      "kind": "type_alias",
      "line_range": [
        486,
        486
      ],
      "name": "CodeBlockLanguageSelectorProps",
      "partial_analysis": false,
      "value": "ComponentProps<typeof Select>;",
      "visibility": "Public"
    },
    {
      "children": [],
      "id": "apps/templates/web-chat-next/components/ai-elements/code-block.tsx:CodeBlockLanguageSelector",
      "is_async": false,
      "kind": "variable",
      "line_range": [
        488,
        490
      ],
      "name": "CodeBlockLanguageSelector",
      "params": [
        {
          "name": "props",
          "optional": false,
          "type": "CodeBlockLanguageSelectorProps"
        }
      ],
      "partial_analysis": false,
      "value": "",
      "visibility": "Public"
    },
    {
      "children": [],
      "id": "apps/templates/web-chat-next/components/ai-elements/code-block.tsx:CodeBlockLanguageSelectorTriggerProps",
      "kind": "type_alias",
      "line_range": [
        492,
        492
      ],
      "name": "CodeBlockLanguageSelectorTriggerProps",
      "partial_analysis": false,
      "value": "ComponentProps<typeof SelectTrigger>;",
      "visibility": "Public"
    },
    {
      "children": [],
      "id": "apps/templates/web-chat-next/components/ai-elements/code-block.tsx:CodeBlockLanguageSelectorTrigger",
      "is_async": false,
      "kind": "variable",
      "line_range": [
        494,
        503
      ],
      "name": "CodeBlockLanguageSelectorTrigger",
      "params": [
        {
          "name": "_",
          "optional": false,
          "type": "CodeBlockLanguageSelectorTriggerProps"
        }
      ],
      "partial_analysis": false,
      "value": "",
      "visibility": "Public"
    },
    {
      "children": [],
      "id": "apps/templates/web-chat-next/components/ai-elements/code-block.tsx:CodeBlockLanguageSelectorValueProps",
      "kind": "type_alias",
      "line_range": [
        505,
        505
      ],
      "name": "CodeBlockLanguageSelectorValueProps",
      "partial_analysis": false,
      "value": "ComponentProps<typeof SelectValue>;",
      "visibility": "Public"
    },
    {
      "children": [],
      "id": "apps/templates/web-chat-next/components/ai-elements/code-block.tsx:CodeBlockLanguageSelectorValue",
      "is_async": false,
      "kind": "variable",
      "line_range": [
        507,
        509
      ],
      "name": "CodeBlockLanguageSelectorValue",
      "params": [
        {
          "name": "props",
          "optional": false,
          "type": "CodeBlockLanguageSelectorValueProps"
        }
      ],
      "partial_analysis": false,
      "value": "",
      "visibility": "Public"
    },
    {
      "children": [],
      "id": "apps/templates/web-chat-next/components/ai-elements/code-block.tsx:CodeBlockLanguageSelectorContentProps",
      "kind": "type_alias",
      "line_range": [
        511,
        511
      ],
      "name": "CodeBlockLanguageSelectorContentProps",
      "partial_analysis": false,
      "value": "ComponentProps<typeof SelectContent>;",
      "visibility": "Public"
    },
    {
      "children": [],
      "id": "apps/templates/web-chat-next/components/ai-elements/code-block.tsx:CodeBlockLanguageSelectorContent",
      "is_async": false,
      "kind": "variable",
      "line_range": [
        513,
        516
      ],
      "name": "CodeBlockLanguageSelectorContent",
      "params": [
        {
          "name": "_",
          "optional": false,
          "type": "CodeBlockLanguageSelectorContentProps"
        }
      ],
      "partial_analysis": false,
      "value": "",
      "visibility": "Public"
    },
    {
      "children": [],
      "id": "apps/templates/web-chat-next/components/ai-elements/code-block.tsx:CodeBlockLanguageSelectorItemProps",
      "kind": "type_alias",
      "line_range": [
        518,
        518
      ],
      "name": "CodeBlockLanguageSelectorItemProps",
      "partial_analysis": false,
      "value": "ComponentProps<typeof SelectItem>;",
      "visibility": "Public"
    },
    {
      "children": [],
      "id": "apps/templates/web-chat-next/components/ai-elements/code-block.tsx:CodeBlockLanguageSelectorItem",
      "is_async": false,
      "kind": "variable",
      "line_range": [
        520,
        522
      ],
      "name": "CodeBlockLanguageSelectorItem",
      "params": [
        {
          "name": "props",
          "optional": false,
          "type": "CodeBlockLanguageSelectorItemProps"
        }
      ],
      "partial_analysis": false,
      "value": "",
      "visibility": "Public"
    }
  ]
}