{
  "HandleMessageStreamEvent": [
    {
      "kind": "type_reference",
      "location": {
        "column": 18,
        "file": "packages/eve/src/client/ndjson.ts",
        "line": 38
      },
      "symbol": "packages/eve/src/protocol/message.ts:HandleMessageStreamEvent"
    },
    {
      "kind": "type_reference",
      "location": {
        "column": 36,
        "file": "packages/eve/src/client/ndjson.ts",
        "line": 66
      },
      "symbol": "packages/eve/src/protocol/message.ts:HandleMessageStreamEvent"
    },
    {
      "kind": "type_reference",
      "location": {
        "column": 36,
        "file": "packages/eve/src/client/ndjson.ts",
        "line": 76
      },
      "symbol": "packages/eve/src/protocol/message.ts:HandleMessageStreamEvent"
    }
  ]
}